setup.cfg
setup.py
Py3Tumblr.egg-info/PKG-INFO
Py3Tumblr.egg-info/SOURCES.txt
Py3Tumblr.egg-info/dependency_links.txt
Py3Tumblr.egg-info/requires.txt
Py3Tumblr.egg-info/top_level.txt
pytumblr/__init__.py
pytumblr/helpers.py
pytumblr/request.py