Metadata-Version: 1.0
Name: Py3Tumblr
Version: 0.0.6
Summary: A Python API v2 wrapper for Tumblr
Home-page: https://github.com/dianakhuang/pytumblr/tree/diana/python-3-support
Author: John Bunting
Author-email: johnb@tumblr.com
License: LICENSE
Platform: UNKNOWN
